doc_helper/__init__.py
doc_helper/doc_helper.py
doc_helper-1.1.1.dist-info/LICENSE
doc_helper-1.1.1.dist-info/METADATA
doc_helper-1.1.1.dist-info/WHEEL
doc_helper-1.1.1.dist-info/top_level.txt
doc_helper-1.1.1.dist-info/RECORD
