Metadata-Version: 2.1
Name: doc-helper
Version: 1.1.1
Summary: Compose docstrings with repeated arguments
Home-page: https://github.com/ynshen/DocHelper/
Author: Yuning Shen
Author-email: ynshen23@gmail.com
License: UNKNOWN
Project-URL: Bug Reports, https://github.com/ynshen/DocHelper/issues/
Project-URL: Source, https://github.com/ynshen/DocHelper/
Keywords: documentation docstring utility
Platform: UNKNOWN
Classifier: License :: OSI Approved :: BSD License
Requires-Python: >=3.5
Requires-Dist: pandas
